grcwjt/__init__.py
grcwjt/grc.py
GRCwjt-0.0.5.dist-info/METADATA
GRCwjt-0.0.5.dist-info/WHEEL
GRCwjt-0.0.5.dist-info/license.txt
GRCwjt-0.0.5.dist-info/top_level.txt
GRCwjt-0.0.5.dist-info/RECORD
