Metadata-Version: 2.1
Name: GRCwjt
Version: 0.0.5
Summary: UNKNOWN
Home-page: UNKNOWN
Author: UNKNOWN
Author-email: UNKNOWN
License: UNKNOWN
Platform: UNKNOWN
Requires-Dist: rpyc
Requires-Dist: pyelftools
Requires-Dist: find-libpython
